exdict/__init__.py
exdict-0.2.dist-info/LICENSE
exdict-0.2.dist-info/METADATA
exdict-0.2.dist-info/WHEEL
exdict-0.2.dist-info/top_level.txt
exdict-0.2.dist-info/RECORD
