Metadata-Version: 2.1
Name: exdict
Version: 0.2
Summary: Extended Dict - dictionary with attributes
Home-page: https://github.com/cristianowa/exdict
Author: Cristiano W. Araujo
Author-email: cristianowerneraraujo@gmail.com
License: UNKNOWN
Download-URL: https://github.com/cristianowa/exdict/archive/0.1.zip
Keywords: dictionary
Platform: UNKNOWN
